{
    "title": "",
    "subsection": [
      {
        "subSectionId": "AssetDataId",
        "subSectionTitle": "Asset Data",
        "mainInfoPath": "/Generic/GetDataViewBySQL",
        "mainInfo": [
          {
            "type": "text",
            "label": "Full Asset Name",
            "property": "FullAssetName"
          },
          {
            "type": "text",
            "label": "Asset Condition",
            "property": "AssetCondition"
          },
          {
            "type": "text",
            "label": "Manufacturing Year",
            "property": "ManufacturingYear"
          },
          {
            "type": "text",
            "label": "Asset Price",
            "property": "AssetPriceAmt"
          },
          {
            "type": "text",
            "label": "Down Payment Type",
            "property": "DownPaymentType"
          },
          {
            "type": "currency",
            "label": "Down Payment",
            "property": "DownPaymentAmt"
          },
          {
            "type": "text",
            "label": "License Plate No.",
            "property": "SerialNo1"
          }
        ],
        "querystring": {
          "name": "viewLeadAssetData"
        }
      }
    ]
  }
