{
    "title": "",
    "subsection": [
      {
        "subSectionId": "CustPersonalJobDataNonProfId",
        "subSectionTitle": "Job Data",
        "mainInfoPath": "/Generic/GetDataViewBySQL",
        "mainInfo": [
          {
            "type": "text",
            "label": "Customer Model",
            "property": "CustModelName"
          },
          {
            "type": "",
            "label": "",
            "property": ""
          },
          {
            "type": "text",
            "label": "Profession",
            "property": "ProfessionName"
          },
          {
            "type": "",
            "label": "",
            "property": ""
          },
          {
            "type": "text",
            "label": "Authority AML",
            "property": "AmlAuthority"
          },
          {
            "type": "text",
            "label": "Bussiness Source AML",
            "property": "AmlBussource"
          },
          {
            "type": "text",
            "label": "Department AML",
            "property": "AmlDepartment"
          },
          {
            "type": "text",
            "label": "Bussiness Period AML",
            "property": "AmlBusPeriod"
          },
          {
            "type": "currency",
            "label": "Estimation Remuneration",
            "property": "EstRemuneration"
          }
        ],
        "querystring": {
          "name": "viewLtkmCustPersonalJobDataNonProf"
        }
      }
    ]
  }
  